LICENSE
MANIFEST.in
README.md
pyproject.toml
setup.cfg
setup.py
pokemon/__init__.py
pokemon/convert.py
pokemon/master.py
pokemon/scripts.py
pokemon/skills.py
pokemon/utils.py
pokemon.egg-info/PKG-INFO
pokemon.egg-info/SOURCES.txt
pokemon.egg-info/dependency_links.txt
pokemon.egg-info/entry_points.txt
pokemon.egg-info/not-zip-safe
pokemon.egg-info/top_level.txt
pokemon/database/pokemons.json
pokemon/database/images/1.jpg
pokemon/database/images/10.jpg
pokemon/database/images/100.jpg
pokemon/database/images/1000.jpg
pokemon/database/images/1001.jpg
pokemon/database/images/1002.jpg
pokemon/database/images/1003.jpg
pokemon/database/images/1004.jpg
pokemon/database/images/1005.jpg
pokemon/database/images/1006.jpg
pokemon/database/images/1007.jpg
pokemon/database/images/1008.jpg
pokemon/database/images/101.jpg
pokemon/database/images/102.jpg
pokemon/database/images/103.jpg
pokemon/database/images/104.jpg
pokemon/database/images/105.jpg
pokemon/database/images/106.jpg
pokemon/database/images/107.jpg
pokemon/database/images/108.jpg
pokemon/database/images/109.jpg
pokemon/database/images/11.jpg
pokemon/database/images/110.jpg
pokemon/database/images/111.jpg
pokemon/database/images/112.jpg
pokemon/database/images/113.jpg
pokemon/database/images/114.jpg
pokemon/database/images/115.jpg
pokemon/database/images/116.jpg
pokemon/database/images/117.jpg
pokemon/database/images/118.jpg
pokemon/database/images/119.jpg
pokemon/database/images/12.jpg
pokemon/database/images/120.jpg
pokemon/database/images/121.jpg
pokemon/database/images/122.jpg
pokemon/database/images/123.jpg
pokemon/database/images/124.jpg
pokemon/database/images/125.jpg
pokemon/database/images/126.jpg
pokemon/database/images/127.jpg
pokemon/database/images/128.jpg
pokemon/database/images/129.jpg
pokemon/database/images/13.jpg
pokemon/database/images/130.jpg
pokemon/database/images/131.jpg
pokemon/database/images/132.jpg
pokemon/database/images/133.jpg
pokemon/database/images/134.jpg
pokemon/database/images/135.jpg
pokemon/database/images/136.jpg
pokemon/database/images/137.jpg
pokemon/database/images/138.jpg
pokemon/database/images/139.jpg
pokemon/database/images/14.jpg
pokemon/database/images/140.jpg
