Metadata-Version: 2.1
Name: pokemon
Version: 0.36
Summary: ascii database of pokemon... in Python!
Home-page: https://github.com/vsoch/pokemon
Author: Vanessa Sochat
Author-email: vsoch@noreply.github.users.com
License: LICENSE
Keywords: pokemon,avatar,ascii,gravatar
Platform: UNKNOWN
License-File: LICENSE
